Metadata-Version: 2.1
Name: dickey-fuller-test
Version: 0.1.0
Summary: Module for Lab2, DA
Home-page: https://twitter.com/vsklamm
Author: Sergey Vasilchenko
Author-email: klammvs@google.com
License: UNKNOWN
Platform: UNKNOWN
